typecov.py
typecov-0.2.1.dist-info/METADATA
typecov-0.2.1.dist-info/WHEEL
typecov-0.2.1.dist-info/entry_points.txt
typecov-0.2.1.dist-info/top_level.txt
typecov-0.2.1.dist-info/RECORD
